pyagender/__init__.py
pyagender/pyagender.py
pyagender/pyagender_cli.py
pyagender/version.py
pyagender/wide_resnet.py
pyagender/pretrained_models/haarcascade_frontalface_default.xml
pyagender/pretrained_models/weights.28-3.73.hdf5
test/__init__.py
test/test_pyagender.py
py_agender-0.0.9.dist-info/LICENSE
py_agender-0.0.9.dist-info/METADATA
py_agender-0.0.9.dist-info/WHEEL
py_agender-0.0.9.dist-info/entry_points.txt
py_agender-0.0.9.dist-info/top_level.txt
py_agender-0.0.9.dist-info/RECORD
