Metadata-Version: 2.1
Name: py-agender
Version: 0.0.9
Summary: Simple opencv & tensorflow based solution to estimate Faces, Age and Gender on pictures
Home-page: https://github.com/aristofun/py-agender
Author: Michael Butlitsky
Author-email: aristofun@yandex.ru
License: UNKNOWN
Platform: UNKNOWN
Classifier: Development Status :: 2 - Pre-Alpha
Classifier: Intended Audience :: Developers
Classifier: Intended Audience :: Education
Classifier: Intended Audience :: Science/Research
Classifier: Environment :: Console
Classifier: Topic :: Scientific/Engineering :: Image Recognition
Classifier: Topic :: Scientific/Engineering :: Artificial Intelligence
Classifier: Topic :: Software Development
Classifier: Topic :: Software Development :: Libraries
Classifier: Topic :: Software Development :: Libraries :: Python Modules
Classifier: Programming Language :: Python :: 3
Classifier: License :: OSI Approved :: MIT License
Classifier: License :: Other/Proprietary License
Classifier: Operating System :: OS Independent
Requires-Dist: numpy (<=1.15.9,>=1.13)
Requires-Dist: Keras (<2.2.5,>=2.2.4)
Requires-Dist: opencv-python (<3.5,>=3.4.2+contrib)
Requires-Dist: twine (>=1.10)
Provides-Extra: cpu
Requires-Dist: tensorflow (<1.19.0,>=1.10.0) ; extra == 'cpu'
Provides-Extra: gpu
Requires-Dist: tensorflow-gpu (<1.19.0,>=1.10.0) ; extra == 'gpu'
